django_fields_iterator/__init__.py
django_fields_iterator/iterator.py
django_fields_iterator/types.py
django_fields_iterator-1.3.1.dist-info/METADATA
django_fields_iterator-1.3.1.dist-info/WHEEL
django_fields_iterator-1.3.1.dist-info/RECORD
