Metadata-Version: 2.4
Name: django-fields-iterator
Version: 1.3.1
Summary: django-fields-iterator provides the FieldsIterator class that allow to iterate on some or all of the fields of a model
Project-URL: Source, https://github.com/didouye/sparkup-back/tree/main/packages/django-fields-iterator
Project-URL: Changelog, https://github.com/didouye/sparkup-back/blob/main/packages/django-fields-iterator/CHANGELOG.md
Author-email: "Stephane \"Twidi\" Angel" <s.angel@twidi.com>
License-Expression: BSD-3-Clause
Classifier: Development Status :: 5 - Production/Stable
Classifier: Framework :: Django
Classifier: Framework :: Django :: 4.2
Classifier: Framework :: Django :: 5.0
Classifier: Framework :: Django :: 5.1
Classifier: Intended Audience :: Developers
Classifier: License :: OSI Approved :: BSD License
Classifier: Operating System :: OS Independent
Classifier: Programming Language :: Python :: 3
Classifier: Programming Language :: Python :: 3.9
Classifier: Programming Language :: Python :: 3.10
Classifier: Programming Language :: Python :: 3.11
Classifier: Programming Language :: Python :: 3.12
Classifier: Topic :: Software Development :: Libraries
Classifier: Topic :: Software Development :: Libraries :: Python Modules
Requires-Python: >=3.9
Requires-Dist: django>=4.2
Provides-Extra: dev
Requires-Dist: pytest-cov>=4.0; extra == 'dev'
Requires-Dist: pytest-django>=4.5; extra == 'dev'
Requires-Dist: pytest>=7.0; extra == 'dev'
Requires-Dist: ruff>=0.1.0; extra == 'dev'
Requires-Dist: twine>=4.0; extra == 'dev'
